odoo10_addon_connector_prestashop-10.0.1.1.0-nspkg.pth
odoo/addons/connector_prestashop/README.rst
odoo/addons/connector_prestashop/__init__.py
odoo/addons/connector_prestashop/__manifest__.py
odoo/addons/connector_prestashop/backend.py
odoo/addons/connector_prestashop/connector.py
odoo/addons/connector_prestashop/components/__init__.py
odoo/addons/connector_prestashop/components/auto_matching_importer.py
odoo/addons/connector_prestashop/components/backend_adapter.py
odoo/addons/connector_prestashop/components/binder.py
odoo/addons/connector_prestashop/components/core.py
odoo/addons/connector_prestashop/components/deleter.py
odoo/addons/connector_prestashop/components/exception.py
odoo/addons/connector_prestashop/components/exporter.py
odoo/addons/connector_prestashop/components/importer.py
odoo/addons/connector_prestashop/components/listener.py
odoo/addons/connector_prestashop/components/mapper.py
odoo/addons/connector_prestashop/components/version_key.py
odoo/addons/connector_prestashop/data/cron.xml
odoo/addons/connector_prestashop/data/ecommerce_data.xml
odoo/addons/connector_prestashop/data/product_decimal_precision.xml
odoo/addons/connector_prestashop/demo/backend.xml
odoo/addons/connector_prestashop/i18n/connector_prestashop.pot
odoo/addons/connector_prestashop/i18n/fr.po
odoo/addons/connector_prestashop/models/__init__.py
odoo/addons/connector_prestashop/models/account_invoice/__init__.py
odoo/addons/connector_prestashop/models/account_invoice/common.py
odoo/addons/connector_prestashop/models/account_invoice/importer.py
odoo/addons/connector_prestashop/models/account_payment_mode/__init__.py
odoo/addons/connector_prestashop/models/account_payment_mode/common.py
odoo/addons/connector_prestashop/models/account_payment_mode/importer.py
odoo/addons/connector_prestashop/models/account_tax/__init__.py
odoo/addons/connector_prestashop/models/account_tax/common.py
odoo/addons/connector_prestashop/models/account_tax/importer.py
odoo10_addon_connector_prestashop-10.0.1.1.0.dist-info/METADATA
odoo10_addon_connector_prestashop-10.0.1.1.0.dist-info/WHEEL
odoo10_addon_connector_prestashop-10.0.1.1.0.dist-info/namespace_packages.txt
odoo10_addon_connector_prestashop-10.0.1.1.0.dist-info/top_level.txt
odoo10_addon_connector_prestashop-10.0.1.1.0.dist-info/RECORD
