Metadata-Version: 2.1
Name: odoo10-addon-connector-prestashop
Version: 10.0.1.1.0
Summary: PrestaShop-Odoo connector
Home-page: https://github.com/OCA/connector-prestashop
Author: Akretion,Camptocamp,AvanzOSC,Tecnativa,Mind And Go,Odoo Community Association (OCA)
Author-email: support@odoo-community.org
License: AGPL-3
Platform: UNKNOWN
Classifier: Programming Language :: Python
Classifier: Framework :: Odoo
Classifier: License :: OSI Approved :: GNU Affero General Public License v3
Requires-Python: ~=2.7
Requires-Dist: bs4
Requires-Dist: freezegun
Requires-Dist: html2text
Requires-Dist: odoo10-addon-base-multi-image
Requires-Dist: odoo10-addon-connector-ecommerce
Requires-Dist: odoo10-addon-product-multi-category
Requires-Dist: odoo10-addon-product-variant-supplierinfo
Requires-Dist: odoo10-addon-stock-available
Requires-Dist: odoo (<10.1dev,>=10.0)
Requires-Dist: prestapyt
Requires-Dist: vcrpy (==1.10.5)
